streamgen/__init__.py
streamgen/enums.py
streamgen/exceptions.py
streamgen/nodes.py
streamgen/parameter/__init__.py
streamgen/parameter/store.py
streamgen/samplers/__init__.py
streamgen/samplers/tree.py
streamgen/streams.py
streamgen/transforms.py
streamgen/visualizations.py
streamgen-1.2.0.dist-info/LICENSE
streamgen-1.2.0.dist-info/METADATA
streamgen-1.2.0.dist-info/WHEEL
streamgen-1.2.0.dist-info/RECORD
