Metadata-Version: 2.3
Name: streamgen
Version: 1.2.0
Summary: 🌌 a framework for generating streams of labeled data.
Home-page: https://github.com/Infineon/StreamGen
License: MIT
Keywords: Python,Data Generation,Data Streams,Continual Learning,Data Structures,Function Composition
Author: Laurenz Farthofer
Author-email: laurenz@hey.com
Requires-Python: >=3.11,<4.0
Classifier: License :: OSI Approved :: MIT License
Classifier: Programming Language :: Python :: 3
Classifier: Programming Language :: Python :: 3.11
Classifier: Programming Language :: Python :: 3.12
Classifier: Programming Language :: Python :: 3.13
Provides-Extra: all
Provides-Extra: cl
Provides-Extra: examples
Requires-Dist: anytree (>=2.7.0)
Requires-Dist: beartype (>=0.18)
Requires-Dist: continuum (>=1.2.7) ; extra == "cl" or extra == "all"
Requires-Dist: graphviz (>=0.20.3)
Requires-Dist: ipympl (>=0.9.4) ; extra == "examples" or extra == "all"
Requires-Dist: loguru (>=0.7.2)
Requires-Dist: matplotlib (>=3.8.3)
Requires-Dist: numpy (>=1.26.4)
Requires-Dist: pandas (>=2.2.1)
Requires-Dist: polars (>=0.20.13) ; extra == "examples" or extra == "all"
Requires-Dist: pytorchcv (>=0.0.67) ; extra == "cl"
Requires-Dist: rich (>=13.7.1)
Requires-Dist: scikit-image (>=0.24) ; extra == "examples" or extra == "all"
Requires-Dist: seaborn (>=0.13.2)
Requires-Dist: torch (>=2.3) ; extra == "cl"
Project-URL: Documentation, https://infineon.github.io/StreamGen/
Project-URL: Repository, https://github.com/Infineon/StreamGen
